setup.cfg
setup.py
bashmath/__init__.py
bashmath/command_tools.py
bashmath.egg-info/PKG-INFO
bashmath.egg-info/SOURCES.txt
bashmath.egg-info/dependency_links.txt
bashmath.egg-info/entry_points.txt
bashmath.egg-info/requires.txt
bashmath.egg-info/top_level.txt