Metadata-Version: 1.0
Name: bashmath
Version: 1.0
Summary: Handy utilities for tabular math in Bash
Home-page: https://github.com/pmitros/bash-math
Author: Piotr Mitros
Author-email: piotr@mitros.org
License: UNKNOWN
Platform: UNKNOWN
